{"key": "aliveedge_diff_d0.1_m0.9_s0.01_r0.85", "records": [{"seed": 0, "kind": "diff", "L_collapsed": true, "R_collapsed": true, "both_alive": false, "either_alive": false, "L_outcome": "LOCK", "R_outcome": "LOCK", "L_collapse_step": 1342, "R_collapse_step": 1259, "mean_theta_LR": 6.915536144971721, "transport": 0.005382301522145869, "L_tvar": 2.8972560585231867e-05, "R_tvar": 2.9547012775704438e-05}, {"seed": 1, "kind": "diff", "L_collapsed": true, "R_collapsed": true, "both_alive": false, "either_alive": false, "L_outcome": "LOCK", "R_outcome": "LOCK", "L_collapse_step": 1083, "R_collapse_step": 1106, "mean_theta_LR": 6.7618072894026975, "transport": 0.005310879741036189, "L_tvar": 2.7787965228956817e-05, "R_tvar": 2.9431850512179642e-05}, {"seed": 2, "kind": "diff", "L_collapsed": true, "R_collapsed": true, "both_alive": false, "either_alive": false, "L_outcome": "LOCK", "R_outcome": "LOCK", "L_collapse_step": 1001, "R_collapse_step": 903, "mean_theta_LR": 6.693647296001052, "transport": 0.005338700979150117, "L_tvar": 2.9168632927166267e-05, "R_tvar": 2.9259764769473097e-05}, {"seed": 3, "kind": "diff", "L_collapsed": true, "R_collapsed": true, "both_alive": false, "either_alive": false, "L_outcome": "LOCK", "R_outcome": "LOCK", "L_collapse_step": 866, "R_collapse_step": 877, "mean_theta_LR": 6.818960111363024, "transport": 0.005333569584562576, "L_tvar": 2.900910269136143e-05, "R_tvar": 2.713288778540471e-05}, {"seed": 4, "kind": "diff", "L_collapsed": true, "R_collapsed": true, "both_alive": false, "either_alive": false, "L_outcome": "LOCK", "R_outcome": "LOCK", "L_collapse_step": 967, "R_collapse_step": 969, "mean_theta_LR": 6.870914883750931, "transport": 0.005358543989343002, "L_tvar": 2.9218627611020538e-05, "R_tvar": 2.749562213150657e-05}, {"seed": 5, "kind": "diff", "L_collapsed": true, "R_collapsed": true, "both_alive": false, "either_alive": false, "L_outcome": "LOCK", "R_outcome": "LOCK", "L_collapse_step": 828, "R_collapse_step": 827, "mean_theta_LR": 6.716045821378955, "transport": 0.0052444131498436885, "L_tvar": 2.8108010439513033e-05, "R_tvar": 2.7177210413048727e-05}, {"seed": 6, "kind": "diff", "L_collapsed": true, "R_collapsed": true, "both_alive": false, "either_alive": false, "L_outcome": "LOCK", "R_outcome": "LOCK", "L_collapse_step": 1034, "R_collapse_step": 1036, "mean_theta_LR": 6.876516438274344, "transport": 0.005341389501870118, "L_tvar": 2.93799145901168e-05, "R_tvar": 2.959018262090781e-05}, {"seed": 7, "kind": "diff", "L_collapsed": true, "R_collapsed": true, "both_alive": false, "either_alive": false, "L_outcome": "LOCK", "R_outcome": "LOCK", "L_collapse_step": 821, "R_collapse_step": 810, "mean_theta_LR": 6.806302157026522, "transport": 0.005342876377646431, "L_tvar": 2.749124018459949e-05, "R_tvar": 2.780222797592783e-05}, {"seed": 8, "kind": "diff", "L_collapsed": true, "R_collapsed": true, "both_alive": false, "either_alive": false, "L_outcome": "LOCK", "R_outcome": "LOCK", "L_collapse_step": 968, "R_collapse_step": 973, "mean_theta_LR": 6.7080913569485645, "transport": 0.00532067322511361, "L_tvar": 2.9254388456191355e-05, "R_tvar": 2.963534449292107e-05}, {"seed": 9, "kind": "diff", "L_collapsed": true, "R_collapsed": true, "both_alive": false, "either_alive": false, "L_outcome": "LOCK", "R_outcome": "LOCK", "L_collapse_step": 1028, "R_collapse_step": 1022, "mean_theta_LR": 6.703587545793136, "transport": 0.005341932739565958, "L_tvar": 2.8801734582979837e-05, "R_tvar": 2.7593902669337448e-05}, {"seed": 10, "kind": "diff", "L_collapsed": true, "R_collapsed": true, "both_alive": false, "either_alive": false, "L_outcome": "LOCK", "R_outcome": "LOCK", "L_collapse_step": 901, "R_collapse_step": 847, "mean_theta_LR": 6.9120792827038, "transport": 0.005230605272205984, "L_tvar": 2.9520367635852698e-05, "R_tvar": 2.941994455492465e-05}, {"seed": 11, "kind": "diff", "L_collapsed": true, "R_collapsed": true, "both_alive": false, "either_alive": false, "L_outcome": "LOCK", "R_outcome": "LOCK", "L_collapse_step": 912, "R_collapse_step": 986, "mean_theta_LR": 6.763466542785622, "transport": 0.00531555601890108, "L_tvar": 2.7737527253681303e-05, "R_tvar": 2.961859648813933e-05}, {"seed": 12, "kind": "diff", "L_collapsed": true, "R_collapsed": true, "both_alive": false, "either_alive": false, "L_outcome": "LOCK", "R_outcome": "LOCK", "L_collapse_step": 861, "R_collapse_step": 944, "mean_theta_LR": 6.941562208467213, "transport": 0.005323560710278777, "L_tvar": 2.870078052876641e-05, "R_tvar": 2.910852151007548e-05}, {"seed": 13, "kind": "diff", "L_collapsed": true, "R_collapsed": true, "both_alive": false, "either_alive": false, "L_outcome": "LOCK", "R_outcome": "LOCK", "L_collapse_step": 969, "R_collapse_step": 944, "mean_theta_LR": 6.546948739057614, "transport": 0.005318217456416052, "L_tvar": 2.878899559573275e-05, "R_tvar": 2.851501197223905e-05}, {"seed": 14, "kind": "diff", "L_collapsed": true, "R_collapsed": true, "both_alive": false, "either_alive": false, "L_outcome": "LOCK", "R_outcome": "LOCK", "L_collapse_step": 687, "R_collapse_step": 654, "mean_theta_LR": 6.848576804623563, "transport": 0.00521136676570668, "L_tvar": 2.8927507094067877e-05, "R_tvar": 2.8943166646980697e-05}, {"seed": 15, "kind": "diff", "L_collapsed": true, "R_collapsed": true, "both_alive": false, "either_alive": false, "L_outcome": "LOCK", "R_outcome": "LOCK", "L_collapse_step": 828, "R_collapse_step": 844, "mean_theta_LR": 6.755898982769986, "transport": 0.005347364698713482, "L_tvar": 2.7674264465677852e-05, "R_tvar": 2.842597654479031e-05}, {"seed": 16, "kind": "diff", "L_collapsed": true, "R_collapsed": true, "both_alive": false, "either_alive": false, "L_outcome": "LOCK", "R_outcome": "LOCK", "L_collapse_step": 813, "R_collapse_step": 873, "mean_theta_LR": 6.579097338600843, "transport": 0.005318762046223095, "L_tvar": 2.9322816147770543e-05, "R_tvar": 2.8804690997261774e-05}, {"seed": 17, "kind": "diff", "L_collapsed": true, "R_collapsed": true, "both_alive": false, "either_alive": false, "L_outcome": "LOCK", "R_outcome": "LOCK", "L_collapse_step": 858, "R_collapse_step": 915, "mean_theta_LR": 6.775239369374107, "transport": 0.005326377150496004, "L_tvar": 2.839721963769521e-05, "R_tvar": 2.8861960956185943e-05}, {"seed": 18, "kind": "diff", "L_collapsed": true, "R_collapsed": true, "both_alive": false, "either_alive": false, "L_outcome": "LOCK", "R_outcome": "LOCK", "L_collapse_step": 923, "R_collapse_step": 933, "mean_theta_LR": 6.703171621035036, "transport": 0.0052882473143012155, "L_tvar": 2.8741518833957244e-05, "R_tvar": 2.9371898200085117e-05}, {"seed": 19, "kind": "diff", "L_collapsed": true, "R_collapsed": true, "both_alive": false, "either_alive": false, "L_outcome": "LOCK", "R_outcome": "LOCK", "L_collapse_step": 1090, "R_collapse_step": 1004, "mean_theta_LR": 6.772306530593295, "transport": 0.005344569889431349, "L_tvar": 2.718405428478871e-05, "R_tvar": 2.9243239095454187e-05}], "meta": {"N": 20, "T": 2500, "sigma": 0.01, "r_sat": 0.85, "delta": 0.1, "mu": 0.9, "done": true}}